{
  "chapter_input": {
    "section_id": "es.grammar.subjunctive_past_counterfactuals",
    "chapter_id": "es.grammar.subjunctive_past_counterfactuals.pluscuamperfecto_de_subjuntivo_unreal_past",
    "title": "Pluscuamperfecto de subjuntivo and unreal past",
    "title_short": "Pluscuamperfecto de subjuntivo and unreal past",
    "level": "B2",
    "order": 137,
    "ui_language": "ru",
    "target_language": "es",
    "prerequisites": [
      "es.grammar.subjunctive_past_counterfactuals.perfect_subjunctive_haya_hecho"
    ]
  }
}
