{
  "chapter_input": {
    "section_id": "es.grammar.non_finite_forms_periphrases",
    "chapter_id": "es.grammar.non_finite_forms_periphrases.periphrases_change_process_seguir_plus_gerundio_acabar_de",
    "title": "Periphrases of change and process: seguir + gerundio, acabar de, volver a, dejar de",
    "title_short": "seguir + gerundio, acabar de, volver a, dejar de",
    "level": "B2",
    "order": 110,
    "ui_language": "ru",
    "target_language": "es",
    "prerequisites": [
      "es.grammar.non_finite_forms_periphrases.participles_adjectives_result_states"
    ]
  }
}
