{
  "theory_block": {
    "id": "b4_theory_gerundio_special_suppletion",
    "concept_id": "gerundio_irregular_suppletive_forms",
    "content_md": "### Когда **-iendo** «ломается»\nЧасть глаголов даёт **особый герундий**: его нельзя надёжно вывести только из инфинитива по шаблону *-ar/-er/-ir*. На уровне A2 полезно зафиксировать короткий **рабочий список**.\n\nЧастые случаи:\n- **e → i** в основе перед *-iendo*: *decir* → *diciendo* [diˈθjen.do] / [diˈsjen.do], *pedir* → *pidiendo* [ˈpi.ðjen.do], *seguir* → *siguiendo* [siˈɡjen.do].\n- **o → u** в основе: *dormir* → *durmiendo* [duɾˈmjen.do], *morir* → *muriendo* [muˈɾjen.do].\n- **Слияние гласных** в *-yendo*: *leer* → *leyendo* [leˈjen.do], *oír* → *oyendo* [oˈjen.do], *caer* → *cayendo* [kaˈjen.do], *traer* → *trayendo* [tɾaˈjen.do].\n- **Совсем другая основа**: *ir* → *yendo* [ˈjen.do] (или [ˈʝen.do] в иных произношениях).\n\nЭто не «исключения ради исключений»: эти формы **очень частотны** в быту (*leyendo*, *diciendo*, *durmiendo*).",
    "key_points": [
      "Три больших типа особых герундиев: **e→i**, **o→u**, **-yendo** после гласной в основе.",
      "*Ir* даёт **yendo**, а не форму по шаблону *-iendo*.",
      "Для произношения опирайтесь на МФА в примерах — так проще не сливать слоги."
    ],
    "common_mistakes": [
      {
        "wrong": "Неправильно: писать или говорить *leendo* по аналогии с *comiendo*.",
        "right": "Правильно: **leyendo** [leˈjen.do] от *leer*.",
        "why": "После гласной в основе испанский выбирает суффикс **-yendo**, а не «двойное *ie*»."
      },
      {
        "wrong": "Неправильно: продлевать чередование настоящего времени в герундии *dormir* и получать *dormiendo*.",
        "right": "Правильно: **durmiendo** [duɾˈmjen.do].",
        "why": "В герундии закреплена основа на **u**, как и в ряде других форм парадигмы *o→u*."
      },
      {
        "wrong": "Неправильно: строить герундий *ir* как *iendo* от основы *i-*.",
        "right": "Правильно: **yendo** [ˈjen.do] (вариант с аффрикатой [ˈʝen.do] встречается в ряде говоров).",
        "why": "Форма **супплетивная**: её нужно запомнить отдельно."
      }
    ],
    "examples": [
      {
        "id": "ex_leyendo",
        "text": "Estoy leyendo las noticias.",
        "translation": "Я читаю новости (сейчас в процессе чтения).",
        "notes": "*Leyendo* [leˈjen.do], не *leendo*.",
        "tags": ["yendo_pattern", "media"]
      },
      {
        "id": "ex_diciendo",
        "text": "¿Qué está diciendo el profesor?",
        "translation": "Что говорит преподаватель (прямо сейчас)?",
        "notes": "*Está diciendo* [esˈta diˈθjen.do] / [esˈta diˈsjen.do] — *e→i* перед *-iendo*.",
        "tags": ["stem_change_gerund", "classroom"]
      },
      {
        "id": "ex_yendo",
        "text": "Ya estamos yendo a la estación.",
        "translation": "Мы уже едем / уже в пути на вокзал.",
        "notes": "*Yendo* [ˈjen.do] от *ir*; *estamos yendo* подчёркивает движение в процессе.",
        "tags": ["ir", "motion"]
      }
    ]
  }
}
