{
  "theory_block": {
    "id": "b5_theory_present_yo_vs_preterite_yo_e",
    "concept_id": "verb_orthography_present_yo_vs_e_ending",
    "content_md": "### Настоящее **yo** и форма на **-é**: держать пару в голове\nДля трёх опорных глаголов удобна **одна строка на лексему**:\n\n- *sacar*: настоящее **yo** *saco* \\[ˈsako\\] — опорная форма **yo** на **-é** *saqué* \\[saˈke\\].\n- *pagar*: *pago* \\[ˈpaɡo\\] — *pagué* \\[paˈɡe\\].\n- *empezar*: *empiezo* \\[emˈpjeθo\\] / \\[emˈpjeso\\] — *empecé* \\[empeˈθe\\] / \\[empeˈse\\].\n\nСмысловой контраст времени в этой главе **вторичен**: важнее **не перепутать буквы**, когда после стема появляется **e**. Полный урок про *pretérito indefinido* придёт позже; здесь формы на **-é** — **логотипы правильной орфографии**.\n\nЕсли вы видите окончание **-o** после **c/g/z**-хвоста стема, чаще вы в настоящем **yo**. Если видите **-é** и нужен звук \\[k\\] или нужное **g** / **z~c** поведение, проверьте **qu / gu / c** по правилам блоков выше.",
    "key_points": [
      "Таблица из трёх пар *saco/saqué*, *pago/pagué*, *empiezo/empecé* — минимум для A1.",
      "Окончание **-o** vs **-é** — быстрый сигнал, какую орфографическую проверку включить.",
      "Полная парадигма прошедшего не обязана быть выучена, но написание опорных форм — да."
    ],
    "common_mistakes": [
      {
        "wrong": "Переносить окончание настоящего **-o** на форму **-é** без смены букв у стема.",
        "right": "При **-é** у **-car/-gar/-zar** включать проверку **qu/gu/c**.",
        "why": "Иначе получаются несуществующие или неверно читаемые формы вроде *sacé*."
      },
      {
        "wrong": "Путать *empiezo* и *empecé*, сводя всё к «ударению».",
        "right": "Разделять: *empiezo* — настоящее с чередованием; *empecé* — опорная **yo** на **-é** с **c**.",
        "why": "Это разные морфемные шаги, их нельзя смешивать."
      }
    ],
    "examples": [
      {
        "id": "ex_pair1",
        "text": "Hoy saco la basura y ayer saqué las entradas.",
        "translation": "Сегодня я выношу мусор, а вчера я достал билеты.",
        "notes": "В одном фрагменте виден контраст **saco / saqué**.",
        "tags": [
          "contrast",
          "car_family"
        ]
      },
      {
        "id": "ex_pair2",
        "text": "Normalmente pago en efectivo, pero ayer pagué con la app.",
        "translation": "Обычно я плачу наличными, но вчера я заплатил через приложение.",
        "notes": "Контраст **pago / pagué**.",
        "tags": [
          "contrast",
          "gar_family"
        ]
      }
    ]
  }
}
