{
  "theory_block": {
    "id": "b6_theory_ru_traps_completed_vs_ongoing",
    "concept_id": "ru_traps_aspect_indefinido_imperfecto",
    "content_md": "Русскоязычным легко путать пару **indefinido/imperfecto** с **видом** глагола. **Совершенный вид** в русском **не равен** автоматически **pretérito indefinido**: русское «он написал» может быть итогом, но испанский выбор зависит от **роли в тексте** (фон vs шаг).\n\nТакже не смешивайте: **один раз в жизни** не всегда indefinido, если вы описываете **длительный процесс внутри того дня**; и наоборот, **повтор** не всегда imperfecto, если вы выделяете **отдельный эпизод** «в тот раз».",
    "key_points": [
      "Перевод на русский — ориентир, но не автоматический переключатель времён.",
      "Смотрите на то, длится ли ситуация как линия или сужается до факта.",
      "Серия однотипных событий в рассказе может требовать разных решений по предложениям."
    ],
    "common_mistakes": [
      {
        "wrong": "Думать: «раз действие завершено в прошлом — значит, всегда indefinido».",
        "right": "Спрашивать: это **фон/процесс** (imperfecto) или **точка сюжета** (indefinido)?",
        "why": "Завершённость в абстрактном смысле не заменяет различие ролей в испанском повествовании."
      }
    ],
    "examples": [
      {
        "id": "ex_b6_1",
        "text": "Ese día trabajaba hasta tarde, pero aun así terminó el informe.",
        "translation": "В тот день он работал допоздна, но всё же закончил отчёт.",
        "notes": "Длительная работа (imperfecto) и завершение как результат (indefinido).",
        "tags": ["ru_contrast", "process_result"]
      },
      {
        "id": "ex_b6_2",
        "text": "Cuando era estudiante, viajaba cada verano; un año visitó Portugal.",
        "translation": "Когда он был студентом, каждое лето путешествовал; один год посетил Португалию.",
        "notes": "Привычная линия (imperfecto) и выделенный эпизод (indefinido).",
        "tags": ["habit", "episode"]
      }
    ]
  }
}
