{
  "theory_block": {
    "id": "b1_theory_ser_core_meanings_a1",
    "concept_id": "ser_core_meanings_a1",
    "content_md": "### Ser как «описание по сути»\nНа уровне A1 удобно думать о **ser** так: мы говорим, *что это такое по умолчанию*, *кто человек в стабильном смысле*, *откуда он родом*, *кем работает*, *из чего предмет сделан*, а также называем *время на часах* и часто *день/дату*.\n\nЭто не про «как я себя чувствую сегодня» и не про «где я сейчас стою». Для таких смыслов чаще нужен **estar** (вы уже тренировали это отдельно).\n\n### Быстрый охват\n- Имя и родственная роль: *Soy Ana*, *Es mi hermana*.\n- Происхождение: *Soy de Moscú*, *Es de Perú*.\n- Профессия/роль: *Es médico*, *Soy estudiante* (артикль обычно не ставят).\n- Материал: *La mesa es de madera*.\n- Время: *Son las tres*; *Hoy es lunes*.",
    "key_points": [
      "Ser чаще описывает устойчивую характеристику, профессию, происхождение и материал.",
      "Ser используется для времени на часах и для названия дня/даты в простой формуле.",
      "Состояние «сейчас» и место «сейчас» на A1 почти всегда — зона estar."
    ],
    "common_mistakes": [
      {
        "wrong": "Неправильно: *Estoy profesora* (если речь о профессии как о постоянной роли).",
        "right": "Правильно: *Soy profesora.*",
        "why": "Профессию в базовой формуле обычно связывают с ser, а не с estar."
      },
      {
        "wrong": "Неправильно: *Está de España* (для происхождения).",
        "right": "Правильно: *Es de España.*",
        "why": "Происхождение в шаблоне «быть из…» строится через ser + de."
      }
    ],
    "examples": [
      {
        "id": "ex_ser1",
        "text": "Soy de Rusia y soy ingeniero.",
        "translation": "Я из России и я инженер (по профессии).",
        "notes": "Происхождение и роль — ser.",
        "tags": ["ser", "origin", "profession"]
      },
      {
        "id": "ex_ser2",
        "text": "La silla es de metal.",
        "translation": "Стул сделан из металла.",
        "notes": "Материал — ser.",
        "tags": ["ser", "material"]
      }
    ]
  }
}
