{
  "theory_block": {
    "id": "b3_theory_location_prepositions_common_patterns",
    "concept_id": "location_prepositions_common_patterns",
    "content_md": "### Предлоги места: делаем фразу точнее\nПосле **estar** часто идут предлоги, которые уточняют положение: **en** (в/на), **al lado de** (рядом с), **cerca de** (близко к), **delante de** (перед), **detrás de** (за).\n\nПолезно запоминать их как готовые куски: *está al lado de...*, *está delante de...*. Тогда фраза собирается быстрее и звучит естественнее.",
    "key_points": [
      "Предлоги места уточняют, где именно находится объект.",
      "Лучше учить предлог сразу с коротким шаблоном после estar.",
      "В бытовой речи чаще всего используются en, al lado de и cerca de."
    ],
    "common_mistakes": [
      {
        "wrong": "Неправильно: *La farmacia está cerca la plaza.*",
        "right": "Правильно: *La farmacia está cerca de la plaza.*",
        "why": "После cerca обязательно ставится de."
      },
      {
        "wrong": "Неправильно: *El coche está delante la casa.*",
        "right": "Правильно: *El coche está delante de la casa.*",
        "why": "Выражение delante de используется целиком, без выпадения de."
      }
    ],
    "examples": [
      {
        "id": "ex1",
        "text": "La tienda está al lado del banco.",
        "translation": "Магазин рядом с банком.",
        "notes": "Точная локализация через al lado de.",
        "tags": [
          "estar",
          "preposition",
          "location"
        ]
      },
      {
        "id": "ex2",
        "text": "Mi silla está delante de la ventana.",
        "translation": "Мой стул перед окном.",
        "notes": "Ориентир в пространстве через delante de.",
        "tags": [
          "estar",
          "preposition",
          "object"
        ]
      }
    ]
  }
}
